finder_enrichment_db_contracts/__init__.py
finder_enrichment_db_contracts/schemas.py
finder_enrichment_db_contracts-0.1.7.dist-info/METADATA
finder_enrichment_db_contracts-0.1.7.dist-info/WHEEL
finder_enrichment_db_contracts-0.1.7.dist-info/top_level.txt
finder_enrichment_db_contracts-0.1.7.dist-info/RECORD
